evals/__init__.py
evals/api.py
evals/base.py
evals/data.py
evals/data_test.py
evals/eval.py
evals/formatting.py
evals/metrics.py
evals/record.py
evals/record_test.py
evals/registry.py
evals/registry_test.py
evals/task_state.py
evals/cli/oaieval.py
evals/cli/oaievalset.py
evals/completion_fns/__init__.py
evals/completion_fns/cot.py
evals/completion_fns/langchain_llm.py
evals/completion_fns/langchain_math.py
evals/completion_fns/openai.py
evals/completion_fns/retrieval.py
evals/completion_fns/solver_completion_fn.py
evals/elsuite/lambada.py
evals/elsuite/multiple_choice.py
evals/elsuite/solver_tools_convo.py
evals/elsuite/translate.py
evals/elsuite/utils.py
evals/elsuite/utils_test.py
evals/elsuite/already_said_that/distractors.py
evals/elsuite/already_said_that/eval.py
evals/elsuite/already_said_that/prompts.py
evals/elsuite/already_said_that/solvers.py
evals/elsuite/already_said_that/test_distractors.py
evals/elsuite/already_said_that/utils.py
evals/elsuite/already_said_that/scripts/gen_data.py
evals/elsuite/already_said_that/scripts/make_plots.py
evals/elsuite/ballots/eval.py
evals/elsuite/ballots/prompts.py
evals/elsuite/ballots/utils.py
evals/elsuite/ballots/scripts/make_plots.py
evals/elsuite/basic/fuzzy_match.py
evals/elsuite/basic/fuzzy_match_test.py
evals/elsuite/basic/includes.py
evals/elsuite/basic/includes_test.py
evals/elsuite/basic/json_match.py
evals/elsuite/basic/json_match_test.py
evals/elsuite/basic/json_validator.py
evals/elsuite/basic/json_validator_test.py
evals/elsuite/basic/match.py
evals/elsuite/basic/match_test.py
evals/elsuite/basic/match_with_solvers.py
evals/elsuite/bluff/eval.py
evals/elsuite/bluff/prompts.py
evals/elsuite/bluff/solver_player.py
evals/elsuite/bluff/strategy_solver.py
evals/elsuite/bluff/bluff/__init__.py
evals/elsuite/bluff/bluff/cards.py
evals/elsuite/bluff/bluff/game.py
evals/elsuite/bluff/bluff/players.py
evals/elsuite/bluff/bluff/round.py
evals/elsuite/bluff/bluff/task_description.py
evals-3.0.1.post1.dist-info/LICENSE.md
evals-3.0.1.post1.dist-info/METADATA
evals-3.0.1.post1.dist-info/WHEEL
evals-3.0.1.post1.dist-info/entry_points.txt
evals-3.0.1.post1.dist-info/top_level.txt
evals-3.0.1.post1.dist-info/RECORD
