Metadata-Version: 2.1
Name: evals
Version: 3.0.1.post1
Project-URL: repository, https://github.com/openai/evals
Requires-Python: >=3.9
License-File: LICENSE.md
Requires-Dist: aiolimiter
Requires-Dist: anthropic
Requires-Dist: backoff
Requires-Dist: beartype >=0.12.0
Requires-Dist: blobfile
Requires-Dist: chess
Requires-Dist: dacite
Requires-Dist: datasets
Requires-Dist: docker
Requires-Dist: evaluate
Requires-Dist: filelock
Requires-Dist: fire
Requires-Dist: flask
Requires-Dist: google-generativeai
Requires-Dist: gymnasium
Requires-Dist: jiwer
Requires-Dist: langchain
Requires-Dist: langdetect
Requires-Dist: lz4
Requires-Dist: matplotlib
Requires-Dist: mock
Requires-Dist: mypy
Requires-Dist: networkx
Requires-Dist: nltk
Requires-Dist: numexpr
Requires-Dist: numpy
Requires-Dist: openai >=1.0.0
Requires-Dist: pandas
Requires-Dist: playwright
Requires-Dist: pydantic
Requires-Dist: pytest
Requires-Dist: pyyaml
Requires-Dist: sacrebleu
Requires-Dist: seaborn
Requires-Dist: snowflake-connector-python[pandas]
Requires-Dist: spacy-universal-sentence-encoder
Requires-Dist: statsmodels
Requires-Dist: termcolor
Requires-Dist: tiktoken
Requires-Dist: tqdm
Requires-Dist: types-PyYAML
Requires-Dist: types-tqdm
Requires-Dist: zstandard
Provides-Extra: formatters
Requires-Dist: black ; extra == 'formatters'
Requires-Dist: isort ; extra == 'formatters'
Requires-Dist: autoflake ; extra == 'formatters'
Requires-Dist: ruff ; extra == 'formatters'
Provides-Extra: torch
Requires-Dist: torch ; extra == 'torch'
